setup.cfg
setup.py
pdftrick/__init__.py
pdftrick/pdftrick.py
pdftrick.egg-info/PKG-INFO
pdftrick.egg-info/SOURCES.txt
pdftrick.egg-info/dependency_links.txt
pdftrick.egg-info/entry_points.txt
pdftrick.egg-info/top_level.txt