Metadata-Version: 1.1
Name: pdftrick
Version: 0.0.2
Summary: One weird PDF trick
Home-page: https://github.com/tingletech/pdftrick
Author: Brian Tingle
Author-email: brian.tingle.cdlib.org@gmail.com
License: BSD
Download-URL: https://github.com/tingletech/pdftrick/tarball/0.0.2
Keywords: PDF compression
Platform: UNKNOWN
